caching.py
consts.py
ctx_util.py
dockerutil.py
eol.py
github_util.py
lookups.py
ocm_util.py
paths.py
util.py
bdba_utils/__init__.py
bdba_utils/assessments.py
bdba_utils/model.py
bdba_utils/rescore.py
bdba_utils/scan.py
bdba_utils/util.py
crypto_extension/__init__.py
crypto_extension/config.py
delivery_gear_utils-0.1264.0.dist-info/licenses/LICENSE
deliverydb_cache/model.py
deliverydb_cache/util.py
k8s/__init__.py
k8s/backlog.py
k8s/logging.py
k8s/model.py
k8s/runtime_artefacts.py
k8s/util.py
odg/__init__.py
odg/crypto_defaults.yaml
odg/cvss.py
odg/defaults.yaml
odg/extensions_cfg.py
odg/extensions_cfg.yaml
odg/filter.py
odg/findings.py
odg/findings_cfg.yaml
odg/labels.py
odg/model.py
odg/ocm_repo_mappings.yaml
odg/profiles.yaml
odg/shared_cfg.py
odg/util.py
osinfo/__init__.py
osinfo/alpine.py
osinfo/model.py
osinfo/paths.py
rescore/__init__.py
rescore/model.py
rescore/utility.py
responsibles_extension/__init__.py
responsibles_extension/filters.py
responsibles_extension/strategies.py
secret_mgmt/__init__.py
secret_mgmt/aws.py
secret_mgmt/bdba.py
secret_mgmt/blackduck.py
secret_mgmt/builtin-role-bindings.yaml
secret_mgmt/delivery_db.py
secret_mgmt/github.py
secret_mgmt/kubernetes.py
secret_mgmt/oauth_cfg.py
secret_mgmt/oci_registry.py
secret_mgmt/ppms.py
secret_mgmt/rbac.py
secret_mgmt/signing_cfg.py
delivery_gear_utils-0.1264.0.dist-info/METADATA
delivery_gear_utils-0.1264.0.dist-info/WHEEL
delivery_gear_utils-0.1264.0.dist-info/top_level.txt
delivery_gear_utils-0.1264.0.dist-info/RECORD
