Metadata-Version: 2.4
Name: delivery-gear-utils
Version: 0.1264.0
Requires-Python: >=3.11
License-File: LICENSE
Requires-Dist: aiohttp
Requires-Dist: boto3
Requires-Dist: cachetools
Requires-Dist: dacite
Requires-Dist: gardener-cicd-libs==1.2740.0
Requires-Dist: github3.py
Requires-Dist: kubernetes
Requires-Dist: requests
Requires-Dist: urllib3
Requires-Dist: watchdog
Requires-Dist: python-dateutil
Requires-Dist: pyyaml
Dynamic: license-file
Dynamic: requires-dist
